index_503/__init__.py
index_503/cache.py
index_503/file.py
index_503/index.py
index_503/main.py
index_503/metadata.py
index_503/page_generator.py
index_503/py.typed
index_503/util.py
index_503/wheel_file.py
index_503-2.6.0.dist-info/LICENSE
index_503-2.6.0.dist-info/METADATA
index_503-2.6.0.dist-info/WHEEL
index_503-2.6.0.dist-info/entry_points.txt
index_503-2.6.0.dist-info/RECORD
