Metadata-Version: 2.3
Name: index-503
Version: 2.6.0
Summary: PEP 503 index builder
License: MIT
Author: J. Nick Koston
Author-email: nick@koston.org
Requires-Python: >=3.9,<4.0
Classifier: Development Status :: 2 - Pre-Alpha
Classifier: Intended Audience :: Developers
Classifier: License :: OSI Approved :: MIT License
Classifier: Natural Language :: English
Classifier: Operating System :: OS Independent
Classifier: Programming Language :: Python :: 3
Classifier: Programming Language :: Python :: 3.9
Classifier: Programming Language :: Python :: 3.10
Classifier: Programming Language :: Python :: 3.11
Classifier: Programming Language :: Python :: 3.12
Classifier: Programming Language :: Python :: 3.13
Classifier: Topic :: Software Development :: Libraries
Requires-Dist: airium (>=0.2.5,<0.3.0)
Requires-Dist: click (>=8.1.3,<9.0.0)
Requires-Dist: consolekit (>=1.4.1,<2.0.0)
Requires-Dist: dist-meta (>=0.8,<0.10)
Requires-Dist: natsort (>=8.3.1,<9.0.0)
Requires-Dist: yarl (>=1.9.2,<2.0.0)
Project-URL: Bug Tracker, https://github.com/bdraco/index-503/issues
Project-URL: Changelog, https://github.com/bdraco/index-503/blob/main/CHANGELOG.md
Project-URL: Documentation, https://index-503.readthedocs.io
Project-URL: Repository, https://github.com/bdraco/index-503
